{
  "0": {
    "names": ["0/0", "-/-"], "person": "none", "current": "-/-"
  },
  "1": {
    "names": ["Wheel of Dortune"], "person": "Rohan", "current": "Wheel of Dortune"
  },
  "6": {
    "names": ["Spicy T"], "person": "Ravi", "current": "Spicy T"
  },
  "3": {
    "names": ["Kennard-ly Wait"], "person": "Sahil", "current": "Kennard-ly Wait"
  },
  "4": {
    "names": ["I'll Have Another"], "person": "Alison", "current": "I'll Have Another"
  },
  "5": {
    "names": ["Lebran Grains"], "person": "AlexK", "current": "Lebran Grains"
  },
  "2": {"names": ["CJ M'Gollum"], "person": "Neil", "current": "CJ M'Gollum"
  },
  "7": {
    "names": ["The Young Bane Rises"], "person": "Chris", "current": "The Young Bane Rises"
  },
  "8": {
    "names": ["The Jive Turkeys"], "person": "John", "current": "The Jive Turkeys"
  },
  "9": {
    "names": ["James's Optimal Team"], "person": "JamesC", "current": "Every \"Derozan\" Has Its Thorn"
  },
  "10": {
    "names": ["SexLand"], "person": "AlexW", "current": "SexLand"
  },
  "11": {
    "names": ["The Bealtles", "Biscuits and Groovy"], "person": "Aaron", "current": "The Bealtles"
  },
  "12": {
    "names": ["James's Unreal Team"], "person": "JamesW", "current": "James's Unreal Team"
  }
}
